{
    "DataSets": [
        {
            "name": "Al_Al_Plate_Gear",
            "folder": "..\\..\\DataSets\\DataFiltered",
            "training_validation_data": [
                "AL_2007_T4_Plate",
                "AL_2007_T4_Plate_Depth",
                "AL_2007_T4_Plate_SF"
            ],
            "testing_data_paths": [
                "AL_2007_T4_Gear_Normal_3.csv"
            ],
            "target_channels": [
                "curr_x"
            ],
            "percentage_used": 100
        },
        {
            "name": "Al_St_Plate_Plate",
            "folder": "..\\..\\DataSets\\DataFiltered",
            "training_validation_data": [
                "AL_2007_T4_Plate",
                "AL_2007_T4_Plate_Depth",
                "AL_2007_T4_Plate_SF"
            ],
            "testing_data_paths": [
                "S235JR_Plate_Normal_3.csv"
            ],
            "target_channels": [
                "curr_x"
            ],
            "percentage_used": 100
        },
        {
            "name": "Al_St_Plate_Gear",
            "folder": "..\\..\\DataSets\\DataFiltered",
            "training_validation_data": [
                "AL_2007_T4_Plate",
                "AL_2007_T4_Plate_Depth",
                "AL_2007_T4_Plate_SF"
            ],
            "testing_data_paths": [
                "S235JR_Gear_Normal_3.csv"
            ],
            "target_channels": [
                "curr_x"
            ],
            "percentage_used": 100
        }
    ],
    "Models": {
        "Neural_Net_Ensemble": {
            "NUMBEROFMODELS": 10,
            "hyperparameters": {
                "learning_rate": 0.001,
                "n_hidden_size": 65,
                "n_hidden_layers": 1
            }
        },
        "Recurrent_Neural_Net_Ensemble": {
            "NUMBEROFMODELS": 10,
            "hyperparameters": {
                "learning_rate": 0.0001,
                "n_hidden_size": 65,
                "n_hidden_layers": 1
            }
        }
    },
    "Data_Preprocessing": {
        "window_size": 10,
        "past_values": 2,
        "future_values": 2
    }
}